securefilecrypt/__init__.py
securefilecrypt/cli.py
securefilecrypt-0.1.7.dist-info/licenses/LICENSE
securefilecrypt-0.1.7.dist-info/METADATA
securefilecrypt-0.1.7.dist-info/WHEEL
securefilecrypt-0.1.7.dist-info/entry_points.txt
securefilecrypt-0.1.7.dist-info/top_level.txt
securefilecrypt-0.1.7.dist-info/RECORD
