Metadata-Version: 2.4
Name: securefilecrypt
Version: 0.1.7
Summary: Secure File Encryption Library
Author-email: diegomarin75 <diegomarin75@gmail.com>
License: MIT License
Project-URL: Homepage, https://github.com/diegomarin75-work/SecureFileCrypt
Project-URL: Issues, https://github.com/diegomarin75-work/SecureFileCrypt/issues
Requires-Python: >=3.7
License-File: LICENSE
Requires-Dist: cryptography>=45.0.6
Dynamic: license-file
